pocket_agent_mcp/__init__.py
pocket_agent_mcp/client.py
pocket_agent_mcp/server.py
pocket_agent_mcp-0.1.2.dist-info/licenses/LICENSE
pocket_agent_mcp-0.1.2.dist-info/METADATA
pocket_agent_mcp-0.1.2.dist-info/WHEEL
pocket_agent_mcp-0.1.2.dist-info/entry_points.txt
pocket_agent_mcp-0.1.2.dist-info/top_level.txt
pocket_agent_mcp-0.1.2.dist-info/RECORD
