Metadata-Version: 2.4
Name: pocket-agent-mcp
Version: 0.1.2
Summary: MCP based Pocket Agent in vector db ( chroma) as storage
Author-email: Vikash Singh <vikash.singh@linuxmail.org>
Project-URL: Homepage, https://github.com/VikashS/pocket_agent_mcp
Project-URL: Repository, https://github.com/VikashS/pocket_agent_mcp
Project-URL: Issues, https://github.com/VikashS/pocket_agent_mcp/issues
Requires-Python: >=3.11
License-File: LICENSE
Requires-Dist: chromadb>=1.1.0
Requires-Dist: fastapi>=0.116.1
Requires-Dist: fastmcp>=2.12.3
Requires-Dist: langchain>=0.3.27
Requires-Dist: langchain-chroma>=0.2.6
Requires-Dist: langchain-community>=0.3.29
Requires-Dist: langchain-mcp-adapters>=0.1.9
Requires-Dist: langchain-ollama>=0.3.8
Requires-Dist: langchain-openai>=0.3.33
Requires-Dist: langgraph>=0.6.7
Requires-Dist: matplotlib>=3.10.6
Requires-Dist: mcp-use[search]>=1.3.10
Requires-Dist: mcp[cli]>=1.14.0
Requires-Dist: numpy>=2.3.3
Requires-Dist: openai>=1.108.1
Requires-Dist: pandas>=2.3.2
Requires-Dist: pypdf2>=3.0.1
Requires-Dist: python-dotenv>=1.1.1
Requires-Dist: requests>=2.32.5
Requires-Dist: scipy>=1.16.2
Requires-Dist: setuptools>=80.9.0
Requires-Dist: streamlit>=1.49.1
Dynamic: license-file
